{
  "model_name": "Gradient Boosting Mejorado",
  "features": [
    "MatchHeadshots",
    "MatchAssists",
    "RoundKills",
    "TeamStartingEquipmentValue"
  ],
  "target": "MatchKills",
  "use_scaler": false,
  "performance": {
    "test_r2": 0.850211225512184,
    "test_rmse": 3.0671069198436247,
    "test_mae": 2.266730072980648
  },
  "target_stats": {
    "min": 0.0,
    "max": 60.0,
    "mean": 9.102322351775465
  },
  "extrapolation_range": {
    "MatchHeadshots": [
      0,
      50
    ],
    "MatchAssists": [
      0,
      30
    ],
    "RoundKills": [
      0,
      5
    ],
    "TeamStartingEquipmentValue": [
      0,
      35000
    ]
  }
}